winmsgbox/__init__.py
winmsgbox-1.0.1.dist-info/licenses/LICENSE
winmsgbox-1.0.1.dist-info/METADATA
winmsgbox-1.0.1.dist-info/WHEEL
winmsgbox-1.0.1.dist-info/top_level.txt
winmsgbox-1.0.1.dist-info/RECORD
