Metadata-Version: 2.4
Name: winmsgbox
Version: 1.0.1
Summary: A simple wrapper for Windows' MessageBoxW in Python
Author: luluwaffless
License:                     GNU AFFERO GENERAL PUBLIC LICENSE
Project-URL: Homepage, https://github.com/luluwaffless/winmsgbox
Classifier: Programming Language :: Python :: 3
Classifier: Operating System :: Microsoft :: Windows
Classifier: License :: OSI Approved :: GNU Affero General Public License v3
Requires-Python: >=3.0
License-File: LICENSE
Dynamic: license-file
